dropblock.py
dropblock_cli-1.0.2.dist-info/METADATA
dropblock_cli-1.0.2.dist-info/WHEEL
dropblock_cli-1.0.2.dist-info/entry_points.txt
dropblock_cli-1.0.2.dist-info/top_level.txt
dropblock_cli-1.0.2.dist-info/RECORD
