Metadata-Version: 2.4
Name: dropblock-cli
Version: 1.0.2
Summary: A cross-platform CLI tool to ignore files and folders in Dropbox
Author-email: Your Name <your.email@example.com>
Maintainer-email: Your Name <your.email@example.com>
License-Expression: MIT
Project-URL: Homepage, https://github.com/Ottermatics/dropbox-ignore-cli
Project-URL: Repository, https://github.com/Ottermatics/dropbox-ignore-cli
Project-URL: Issues, https://github.com/Ottermatics/dropbox-ignore-cli/issues
Keywords: dropbox,ignore,sync,cli,utility
Classifier: Programming Language :: Python :: 3
Classifier: Programming Language :: Python :: 3.8
Classifier: Programming Language :: Python :: 3.9
Classifier: Programming Language :: Python :: 3.10
Classifier: Programming Language :: Python :: 3.11
Classifier: Programming Language :: Python :: 3.12
Classifier: Operating System :: OS Independent
Classifier: Environment :: Console
Classifier: Intended Audience :: Developers
Classifier: Topic :: Utilities
Classifier: Topic :: System :: Filesystems
Requires-Python: >=3.8
Provides-Extra: dev
Requires-Dist: black>=23.0.0; extra == "dev"
Provides-Extra: test
Requires-Dist: pytest>=7.0.0; extra == "test"
Requires-Dist: pytest-cov>=4.0.0; extra == "test"
